simplaz-0.3.0.dist-info/METADATA
simplaz-0.3.0.dist-info/WHEEL
simplaz/__init__.py
simplaz/simplaz.cpython-36m-darwin.so
simplaz-0.3.0.dist-info/RECORD
